{
    "KPlugin": {
        "MimeTypes": [
            "application/octet-stream",
            "inode/directory"
        ],
        "Name": "Restore Previous Version…",
        "Name[ar]": "استعد الإصدارة السابقة…",
        "Name[ca]": "Restaura la versió anterior…",
        "Name[eu]": "Lehengoratu aurreko bertsioa…",
        "Name[fr]": "Restaurer la version précédente...",
        "Name[he]": "שחזור גרסה קודמת…",
        "Name[it]": "Ripristina versione precedente...",
        "Name[nl]": "Herstel vorige versie…",
        "Name[pt_BR]": "Restaurar versão anterior…",
        "Name[sl]": "Obnovi prejšnjo različico…",
        "Name[sv]": "Återställ föregående version…",
        "Name[tr]": "Önceki Sürümü Geri Yükle…",
        "Name[uk]": "Відновити попередню версію…",
        "Name[zh_CN]": "还原上一个版本…",
        "ServiceTypes": [
            "KFileItemAction/Plugin"
        ]
    },
    "MimeType": "application/octet-stream;inode/directory;"
}
