{
    "KPlugin": {
        "MimeTypes": [
            "application/octet-stream",
            "inode/directory"
        ],
        "Name": "kupfileitemaction",
        "Name[ca@valencia]": "kupfileitemaction",
        "Name[ca]": "kupfileitemaction",
        "Name[fr]": "kupfileitemaction",
        "Name[nl]": "kupfileitemaction",
        "Name[pt_BR]": "kupfileitemaction",
        "Name[sl]": "kupfileitemaction",
        "Name[sv]": "kupfileitemaction",
        "Name[tr]": "Kup Dosya Ögesi Eylemi",
        "Name[uk]": "kupfileitemaction",
        "Name[zh_CN]": "kupfileitemaction",
        "ServiceTypes": [
            "KFileItemAction/Plugin"
        ]
    },
    "MimeType": "application/octet-stream;inode/directory;"
}
